pepycli/__init__.py
pepycli/api.py
pepycli/cli.py
pepycli/config.py
pepycli-0.1.0.dist-info/METADATA
pepycli-0.1.0.dist-info/WHEEL
pepycli-0.1.0.dist-info/entry_points.txt
pepycli-0.1.0.dist-info/top_level.txt
pepycli-0.1.0.dist-info/RECORD
