Metadata-Version: 2.4
Name: pepycli
Version: 0.1.0
Summary: CLI Util for get analytics from pepy.tech
Author-email: Kirill <kirisa49@gmail.com>
Project-URL: HomePage, https://github.com/kirillysz/pepycli
Project-URL: Documentation, https://github.com/kirillysz/pepycli
Requires-Python: >=3.12
Requires-Dist: aiohttp>=3.12.15
Requires-Dist: python-dotenv>=1.1.1
Requires-Dist: typer>=0.16.1
